Workbook

Sheet May 2026 Daily Log
A1: 🚗 RIDESHARE EARNINGS TRACKER — MAY 2026
A2: May 2026 | 01/05/2026 – 31/05/2026
A3: Blue text = enter your data | Teal = Earnings | Red = Expenses | Green = Net Income
A4: Date | B4: Day | C4: Uber Fares ($) | D4: Lyft Fares ($) | E4: Gross Earnings ($) | F4: Start Odo (km) | G4: End Odo (km) | H4: Distance (km) | I4: Gas ($) | J4: Car Wash ($) | K4: Maintenance ($) | L4: Other Expense ($) | M4: Total Expense ($) | N4: Net Income ($) | O4: Hours Driven
A5: 01/05/2026 | B5: Friday | C5: 0 | D5: 0 | E5: =C5+D5 -> 0 | F5: 0 | G5: 0 | H5: =G5-F5 -> 0 | I5: 0 | J5: 0 | K5: 0 | L5: 0 | M5: =I5+J5+K5+L5 -> 0 | N5: =E5-M5 -> 0 | O5: 0
A6: 02/05/2026 | B6: Saturday | C6: 0 | D6: 0 | E6: =C6+D6 -> 0 | F6: 0 | G6: 0 | H6: =G6-F6 -> 0 | I6: 0 | J6: 0 | K6: 0 | L6: 0 | M6: =I6+J6+K6+L6 -> 0 | N6: =E6-M6 -> 0 | O6: 0
A7: 03/05/2026 | B7: Sunday | C7: 0 | D7: 0 | E7: =C7+D7 -> 0 | F7: 0 | G7: 0 | H7: =G7-F7 -> 0 | I7: 0 | J7: 0 | K7: 0 | L7: 0 | M7: =I7+J7+K7+L7 -> 0 | N7: =E7-M7 -> 0 | O7: 0
A8: 04/05/2026 | B8: Monday | C8: 0 | D8: 0 | E8: =C8+D8 -> 0 | F8: 0 | G8: 0 | H8: =G8-F8 -> 0 | I8: 0 | J8: 0 | K8: 0 | L8: 0 | M8: =I8+J8+K8+L8 -> 0 | N8: =E8-M8 -> 0 | O8: 0
A9: 05/05/2026 | B9: Tuesday | C9: 0 | D9: 0 | E9: =C9+D9 -> 0 | F9: 0 | G9: 0 | H9: =G9-F9 -> 0 | I9: 0 | J9: 0 | K9: 0 | L9: 0 | M9: =I9+J9+K9+L9 -> 0 | N9: =E9-M9 -> 0 | O9: 0
A10: 06/05/2026 | B10: Wednesday | C10: 0 | D10: 0 | E10: =C10+D10 -> 0 | F10: 0 | G10: 0 | H10: =G10-F10 -> 0 | I10: 0 | J10: 0 | K10: 0 | L10: 0 | M10: =I10+J10+K10+L10 -> 0 | N10: =E10-M10 -> 0 | O10: 0
A11: 07/05/2026 | B11: Thursday | C11: 0 | D11: 0 | E11: =C11+D11 -> 0 | F11: 0 | G11: 0 | H11: =G11-F11 -> 0 | I11: 0 | J11: 0 | K11: 0 | L11: 0 | M11: =I11+J11+K11+L11 -> 0 | N11: =E11-M11 -> 0 | O11: 0
A12: 08/05/2026 | B12: Friday | C12: 0 | D12: 0 | E12: =C12+D12 -> 0 | F12: 0 | G12: 0 | H12: =G12-F12 -> 0 | I12: 0 | J12: 0 | K12: 0 | L12: 0 | M12: =I12+J12+K12+L12 -> 0 | N12: =E12-M12 -> 0 | O12: 0
A13: 09/05/2026 | B13: Saturday | C13: 0 | D13: 0 | E13: =C13+D13 -> 0 | F13: 0 | G13: 0 | H13: =G13-F13 -> 0 | I13: 0 | J13: 0 | K13: 0 | L13: 0 | M13: =I13+J13+K13+L13 -> 0 | N13: =E13-M13 -> 0 | O13: 0
A14: 10/05/2026 | B14: Sunday | C14: 0 | D14: 0 | E14: =C14+D14 -> 0 | F14: 0 | G14: 0 | H14: =G14-F14 -> 0 | I14: 0 | J14: 0 | K14: 0 | L14: 0 | M14: =I14+J14+K14+L14 -> 0 | N14: =E14-M14 -> 0 | O14: 0
A15: 11/05/2026 | B15: Monday | C15: 0 | D15: 0 | E15: =C15+D15 -> 0 | F15: 0 | G15: 0 | H15: =G15-F15 -> 0 | I15: 0 | J15: 0 | K15: 0 | L15: 0 | M15: =I15+J15+K15+L15 -> 0 | N15: =E15-M15 -> 0 | O15: 0
A16: 12/05/2026 | B16: Tuesday | C16: 0 | D16: 0 | E16: =C16+D16 -> 0 | F16: 0 | G16: 0 | H16: =G16-F16 -> 0 | I16: 0 | J16: 0 | K16: 0 | L16: 0 | M16: =I16+J16+K16+L16 -> 0 | N16: =E16-M16 -> 0 | O16: 0
... A35: 31/05/2026 | B35: Sunday | C35: 0 | D35: 0 | E35: =C35+D35 -> 0 | F35: 0 | G35: 0 | H35: =G35-F35 -> 0 | I35: 0 | J35: 0 | K35: 0 | L35: 0 | M35: =I35+J35+K35+L35 -> 0 | N35: =E35-M35 -> 0 | O35: 0
A36: MAY TOTALS | C36: =SUM(C5:C35) -> 0 | D36: =SUM(D5:D35) -> 0 | E36: =SUM(E5:E35) -> 0 | F36: =SUM(F5:F35) -> 0 | G36: =SUM(G5:G35) -> 0 | H36: =SUM(H5:H35) -> 0 | I36: =SUM(I5:I35) -> 0 | J36: =SUM(J5:J35) -> 0 | ... O36: =SUM(O5:O35) -> 0
A37: $/Hour | N37: =IF(O36>0,N36/O36,0) -> 0 | O37: =O36 -> 0

Sheet May Monthly Summary
A1: 📅 MAY 2026 — MONTHLY SUMMARY
A2: EARNINGS
A3: Uber Fares | B3: ='May 2026 Daily Log'!C36 -> 0
A4: Lyft Fares | B4: ='May 2026 Daily Log'!D36 -> 0
A5: Gross Earnings | B5: ='May 2026 Daily Log'!E36 -> 0 | C5: Uber + Lyft (auto from Daily Log)
A6: ──────── EXPENSES ──────────
A7: Phone & Data Bill | B7: 0 | C7: ← Enter monthly phone/data bill here
A8: Gas | B8: ='May 2026 Daily Log'!I36 -> 0 | C8: Auto from Daily Log
A9: Car Wash | B9: ='May 2026 Daily Log'!J36 -> 0
A10: Maintenance | B10: ='May 2026 Daily Log'!K36 -> 0
A11: Other Expenses | B11: ='May 2026 Daily Log'!L36 -> 0
A12: Monthly Insurance | B12: 0 | C12: ← Enter monthly insurance cost
A13: Car Finance | B13: 0 | C13: ← Enter monthly car finance/lease payment
A14: Total Expenses | B14: =B7+B8+B9+B10+B11+B12+B13 -> 0 | C14: All expenses including insurance & finance
A15: ──────── PERFORMANCE ───────
A16: Net Income | B16: =B5-B14 -> 0 | C16: Gross − Total Expenses (all deducted)
A17: Hours Driven | B17: ='May 2026 Daily Log'!O36 -> 0
A18: $/Hour | B18: =IF(B17>0,B16/B17,0) -> 0 | C18: Net Income ÷ Hours Driven
A19: Expense Ratio | B19: =IF(B5>0,B14/B5,0) -> 0 | C19: Total Expenses ÷ Gross Earnings
A20: Distance Driven (km) | B20: ='May 2026 Daily Log'!H36 -> 0

Sheet Driver Dashboard
B2: 🏆 DRIVER PERFORMANCE DASHBOARD
B3: May 2026 — powered by your Daily Log
B5: Total Gross Earnings | F5: Total Expenses
B6: ='May Monthly Summary'!B5 -> 0 | F6: ='May Monthly Summary'!B14 -> 0
B8: Net Income | F8: Total Hours Driven
B9: ='May Monthly Summary'!B16 -> 0 | F9: ='May Monthly Summary'!B17 -> 0
B11: Average $/Hour | F11: Total Trips
B12: =IF('May Monthly Summary'!B17>0,'May Monthly Summary'!B16/'May Monthly Summary'!B17,0) -> 0 | F12: 0
B14: Expense Ratio | F14: Net Margin
B15: =IF('May Monthly Summary'!B5>0,'May Monthly Summary'!B14/'May Monthly Summary'!B5,0) -> 0 | F15: =IF('May Monthly Summary'!B5>0,'May Monthly Summary'!B16/'May Monthly Summary'!B5,0) -> 0
B18: COLOR LEGEND
B19: Blue text | C19: Hardcoded input cells — enter your data here
B20: Teal shading | C20: Earnings / Gross totals
B21: Red shading | C21: Expense cells
B22: Green shading | C22: Net income / profit
B23: Yellow shading | C23: Key assumption cells
